rpmeta/__init__.py
rpmeta/config.py
rpmeta/constants.py
rpmeta/dataset.py
rpmeta/fetcher.py
rpmeta/helpers.py
rpmeta/model.py
rpmeta/server.py
rpmeta/cli/__init__.py
rpmeta/cli/fetcher.py
rpmeta/cli/main.py
rpmeta/cli/model.py
rpmeta/cli/trainer.py
rpmeta/train/__init__.py
rpmeta/train/base.py
rpmeta/train/models.py
rpmeta/train/trainer.py
rpmeta/train/visualizer.py
rpmeta-0.1.0.dist-info/METADATA
rpmeta-0.1.0.dist-info/WHEEL
rpmeta-0.1.0.dist-info/entry_points.txt
rpmeta-0.1.0.dist-info/licenses/LICENSE
rpmeta-0.1.0.dist-info/RECORD
